haip/__init__.py
haip/config.py
haip_config-0.1.9.dist-info/LICENSE
haip_config-0.1.9.dist-info/METADATA
haip_config-0.1.9.dist-info/WHEEL
haip_config-0.1.9.dist-info/top_level.txt
haip_config-0.1.9.dist-info/RECORD
