Metadata-Version: 2.1
Name: haip-config
Version: 0.1.9
Summary: A simple yaml config manager.
Home-page: https://github.com/haipdev/config
Author: Reinhard Hainz
Author-email: reinhard.hainz@gmail.com
License: UNKNOWN
Platform: UNKNOWN
Classifier: Programming Language :: Python :: 3
Classifier: License :: OSI Approved :: MIT License
Classifier: Operating System :: OS Independent
Requires-Dist: poyo (>=0.4.2)
